{
  "minecraft:recipes/transportation/acacia_boat": {
    "criteria": {
      "in_water": "2022-07-11 22:55:13 +0900"
    },
    "done": true
  },
  "minecraft:recipes/transportation/oak_boat": {
    "criteria": {
      "in_water": "2022-07-11 22:55:13 +0900"
    },
    "done": true
  },
  "minecraft:recipes/transportation/dark_oak_boat": {
    "criteria": {
      "in_water": "2022-07-11 22:55:13 +0900"
    },
    "done": true
  },
  "minecraft:adventure/root": {
    "criteria": {
      "killed_by_something": "2022-07-11 22:53:42 +0900"
    },
    "done": true
  },
  "minecraft:recipes/transportation/birch_boat": {
    "criteria": {
      "in_water": "2022-07-11 22:55:13 +0900"
    },
    "done": true
  },
  "minecraft:recipes/transportation/jungle_boat": {
    "criteria": {
      "in_water": "2022-07-11 22:55:13 +0900"
    },
    "done": true
  },
  "minecraft:recipes/transportation/mangrove_boat": {
    "criteria": {
      "in_water": "2022-07-11 22:55:13 +0900"
    },
    "done": true
  },
  "minecraft:recipes/transportation/spruce_boat": {
    "criteria": {
      "in_water": "2022-07-11 22:55:13 +0900"
    },
    "done": true
  },
  "minecraft:adventure/adventuring_time": {
    "criteria": {
      "minecraft:plains": "2022-07-11 22:53:18 +0900"
    },
    "done": false
  },
  "minecraft:story/root": {
    "criteria": {
      "crafting_table": "2022-07-11 22:57:24 +0900"
    },
    "done": true
  },
  "DataVersion": 3105
}